{
	"$schema": "http://schema.management.azure.com/schemas/2015-01-01/deploymentTemplate.json#",
	"contentVersion": "1.0.0.0",
	"parameters": {
		"factoryName": {
			"type": "string",
			"metadata": "Data Factory Name",
			"defaultValue": "tsrmadf"
		},
		"AzureBlobStorage1_connectionString": {
			"type": "secureString",
			"metadata": "Secure string for 'connectionString' of 'AzureBlobStorage1'"
		},
		"AzureSqlDatabase1_connectionString": {
			"type": "secureString",
			"metadata": "Secure string for 'connectionString' of 'AzureSqlDatabase1'"
		}
	},
	"variables": {
		"factoryId": "[concat('Microsoft.DataFactory/factories/', parameters('factoryName'))]"
	},
	"resources": [
		{
			"name": "[concat(parameters('factoryName'), '/CopySQLToBlob')]",
			"type": "Microsoft.DataFactory/factories/pipelines",
			"apiVersion": "2018-06-01",
			"properties": {
				"activities": [
					{
						"name": "Copy Table To Blob  From SQLDB",
						"type": "Copy",
						"dependsOn": [],
						"policy": {
							"timeout": "7.00:00:00",
							"retry": 0,
							"retryIntervalInSeconds": 30,
							"secureOutput": false,
							"secureInput": false
						},
						"userProperties": [
							{
								"name": "Source",
								"value": "SalesLT.Customer"
							},
							{
								"name": "Destination",
								"value": "storesalessource//cust.csv"
							}
						],
						"typeProperties": {
							"source": {
								"type": "AzureSqlSource"
							},
							"sink": {
								"type": "DelimitedTextSink",
								"storeSettings": {
									"type": "AzureBlobStorageWriteSettings"
								},
								"formatSettings": {
									"type": "DelimitedTextWriteSettings",
									"quoteAllText": true,
									"fileExtension": ".txt"
								}
							},
							"enableStaging": false
						},
						"inputs": [
							{
								"referenceName": "SourceDataset_h9w",
								"type": "DatasetReference",
								"parameters": {}
							}
						],
						"outputs": [
							{
								"referenceName": "DestinationDataset_h9w",
								"type": "DatasetReference",
								"parameters": {}
							}
						]
					},
					{
						"name": "Copy File From Blob to another sqldb",
						"type": "Copy",
						"dependsOn": [
							{
								"activity": "Copy Table To Blob  From SQLDB",
								"dependencyConditions": [
									"Succeeded"
								]
							}
						],
						"policy": {
							"timeout": "7.00:00:00",
							"retry": 0,
							"retryIntervalInSeconds": 30,
							"secureOutput": false,
							"secureInput": false
						},
						"userProperties": [],
						"typeProperties": {
							"source": {
								"type": "DelimitedTextSource",
								"storeSettings": {
									"type": "AzureBlobStorageReadSettings",
									"recursive": true
								},
								"formatSettings": {
									"type": "DelimitedTextReadSettings"
								}
							},
							"sink": {
								"type": "AzureSqlSink"
							},
							"enableStaging": false,
							"translator": {
								"type": "TabularTranslator",
								"mappings": [
									{
										"source": {
											"name": "CustomerID",
											"type": "String"
										},
										"sink": {
											"name": "CustomerID",
											"type": "Int32"
										}
									},
									{
										"source": {
											"name": "NameStyle",
											"type": "String"
										},
										"sink": {
											"name": "NameStyle",
											"type": "Boolean"
										}
									},
									{
										"source": {
											"name": "Title",
											"type": "String"
										},
										"sink": {
											"name": "Title",
											"type": "String"
										}
									},
									{
										"source": {
											"name": "FirstName",
											"type": "String"
										},
										"sink": {
											"name": "FirstName",
											"type": "String"
										}
									},
									{
										"source": {
											"name": "MiddleName",
											"type": "String"
										},
										"sink": {
											"name": "MiddleName",
											"type": "String"
										}
									},
									{
										"source": {
											"name": "LastName",
											"type": "String"
										},
										"sink": {
											"name": "LastName",
											"type": "String"
										}
									},
									{
										"source": {
											"name": "Suffix",
											"type": "String"
										},
										"sink": {
											"name": "Suffix",
											"type": "String"
										}
									},
									{
										"source": {
											"name": "CompanyName",
											"type": "String"
										},
										"sink": {
											"name": "CompanyName",
											"type": "String"
										}
									},
									{
										"source": {
											"name": "SalesPerson",
											"type": "String"
										},
										"sink": {
											"name": "SalesPerson",
											"type": "String"
										}
									},
									{
										"source": {
											"name": "EmailAddress",
											"type": "String"
										},
										"sink": {
											"name": "EmailAddress",
											"type": "String"
										}
									},
									{
										"source": {
											"name": "Phone",
											"type": "String"
										},
										"sink": {
											"name": "Phone",
											"type": "String"
										}
									},
									{
										"source": {
											"name": "PasswordHash",
											"type": "String"
										},
										"sink": {
											"name": "PasswordHash",
											"type": "String"
										}
									},
									{
										"source": {
											"name": "PasswordSalt",
											"type": "String"
										},
										"sink": {
											"name": "PasswordSalt",
											"type": "String"
										}
									},
									{
										"source": {
											"name": "rowguid",
											"type": "String"
										},
										"sink": {
											"name": "rowguid",
											"type": "Guid"
										}
									},
									{
										"source": {
											"name": "ModifiedDate",
											"type": "String"
										},
										"sink": {
											"name": "ModifiedDate",
											"type": "DateTime"
										}
									}
								]
							}
						},
						"inputs": [
							{
								"referenceName": "DestinationDataset_h9w",
								"type": "DatasetReference",
								"parameters": {}
							}
						],
						"outputs": [
							{
								"referenceName": "AzureSqlTable1",
								"type": "DatasetReference",
								"parameters": {}
							}
						]
					}
				],
				"annotations": []
			},
			"dependsOn": [
				"[concat(variables('factoryId'), '/datasets/SourceDataset_h9w')]",
				"[concat(variables('factoryId'), '/datasets/DestinationDataset_h9w')]",
				"[concat(variables('factoryId'), '/datasets/AzureSqlTable1')]"
			]
		},
		{
			"name": "[concat(parameters('factoryName'), '/AzureSqlTable1')]",
			"type": "Microsoft.DataFactory/factories/datasets",
			"apiVersion": "2018-06-01",
			"properties": {
				"linkedServiceName": {
					"referenceName": "AzureSqlDatabase1",
					"type": "LinkedServiceReference"
				},
				"annotations": [],
				"type": "AzureSqlTable",
				"schema": [
					{
						"name": "CustomerID",
						"type": "int",
						"precision": 10
					},
					{
						"name": "NameStyle",
						"type": "bit"
					},
					{
						"name": "Title",
						"type": "nvarchar"
					},
					{
						"name": "FirstName",
						"type": "nvarchar"
					},
					{
						"name": "MiddleName",
						"type": "nvarchar"
					},
					{
						"name": "LastName",
						"type": "nvarchar"
					},
					{
						"name": "Suffix",
						"type": "nvarchar"
					},
					{
						"name": "CompanyName",
						"type": "nvarchar"
					},
					{
						"name": "SalesPerson",
						"type": "nvarchar"
					},
					{
						"name": "EmailAddress",
						"type": "nvarchar"
					},
					{
						"name": "Phone",
						"type": "nvarchar"
					},
					{
						"name": "PasswordHash",
						"type": "varchar"
					},
					{
						"name": "PasswordSalt",
						"type": "varchar"
					},
					{
						"name": "rowguid",
						"type": "uniqueidentifier"
					},
					{
						"name": "ModifiedDate",
						"type": "datetime",
						"precision": 23,
						"scale": 3
					}
				],
				"typeProperties": {
					"schema": "dbo",
					"table": "MyCustoer"
				}
			},
			"dependsOn": [
				"[concat(variables('factoryId'), '/linkedServices/AzureSqlDatabase1')]"
			]
		},
		{
			"name": "[concat(parameters('factoryName'), '/DestinationDataset_h9w')]",
			"type": "Microsoft.DataFactory/factories/datasets",
			"apiVersion": "2018-06-01",
			"properties": {
				"linkedServiceName": {
					"referenceName": "AzureBlobStorage1",
					"type": "LinkedServiceReference"
				},
				"annotations": [],
				"type": "DelimitedText",
				"typeProperties": {
					"location": {
						"type": "AzureBlobStorageLocation",
						"fileName": "cust.csv",
						"container": "storesalessource"
					},
					"columnDelimiter": ",",
					"escapeChar": "\\",
					"firstRowAsHeader": true,
					"quoteChar": "\""
				},
				"schema": []
			},
			"dependsOn": [
				"[concat(variables('factoryId'), '/linkedServices/AzureBlobStorage1')]"
			]
		},
		{
			"name": "[concat(parameters('factoryName'), '/SourceDataset_h9w')]",
			"type": "Microsoft.DataFactory/factories/datasets",
			"apiVersion": "2018-06-01",
			"properties": {
				"linkedServiceName": {
					"referenceName": "AzureSqlDatabase1",
					"type": "LinkedServiceReference"
				},
				"annotations": [],
				"type": "AzureSqlTable",
				"schema": [],
				"typeProperties": {
					"schema": "SalesLT",
					"table": "Customer"
				}
			},
			"dependsOn": [
				"[concat(variables('factoryId'), '/linkedServices/AzureSqlDatabase1')]"
			]
		},
		{
			"name": "[concat(parameters('factoryName'), '/AzureBlobStorage1')]",
			"type": "Microsoft.DataFactory/factories/linkedServices",
			"apiVersion": "2018-06-01",
			"properties": {
				"annotations": [],
				"type": "AzureBlobStorage",
				"typeProperties": {
					"connectionString": "[parameters('AzureBlobStorage1_connectionString')]"
				}
			},
			"dependsOn": []
		},
		{
			"name": "[concat(parameters('factoryName'), '/AzureSqlDatabase1')]",
			"type": "Microsoft.DataFactory/factories/linkedServices",
			"apiVersion": "2018-06-01",
			"properties": {
				"annotations": [],
				"type": "AzureSqlDatabase",
				"typeProperties": {
					"connectionString": "[parameters('AzureSqlDatabase1_connectionString')]"
				}
			},
			"dependsOn": []
		}
	]
}